ez_constructs/__init__.py
ez_constructs/py.typed
ez_constructs/_jsii/__init__.py
ez_constructs/_jsii/ez-constructs@0.0.64.jsii.tgz
ez_constructs-0.0.64.dist-info/LICENSE
ez_constructs-0.0.64.dist-info/METADATA
ez_constructs-0.0.64.dist-info/WHEEL
ez_constructs-0.0.64.dist-info/top_level.txt
ez_constructs-0.0.64.dist-info/RECORD
